LICENSE
MANIFEST.in
README.md
pyproject.toml
setup.cfg
setup.py
django_referral_system.egg-info/PKG-INFO
django_referral_system.egg-info/SOURCES.txt
django_referral_system.egg-info/dependency_links.txt
django_referral_system.egg-info/requires.txt
django_referral_system.egg-info/top_level.txt
referrals/__init__.py
referrals/admin.py
referrals/apps.py
referrals/choices.py
referrals/config.py
referrals/enums.py
referrals/exceptions.py
referrals/helpers.py
referrals/models.py
referrals/serializers.py
referrals/tests.py
referrals/urls.py
referrals/utils.py
referrals/views.py
referrals/migrations/0001_initial.py
referrals/migrations/0002_alter_payoutmethod_method_and_more.py
referrals/migrations/__init__.py
referrals/migrations/__pycache__/0001_initial.cpython-310.pyc
referrals/migrations/__pycache__/__init__.cpython-310.pyc
referrals/repositories/__init__.py
referrals/repositories/base_repository.py
referrals/repositories/promoter_commission_repository.py
referrals/repositories/promoter_payout_repository.py
referrals/repositories/promoter_repository.py
referrals/repositories/referral_repository.py
referrals/services/__init__.py
referrals/services/promoter_payout_service.py
referrals/services/promoter_service.py
referrals/services/referral_service.py