Metadata-Version: 2.1
Name: django-referral-system
Version: 0.1.1
Summary: A Django app for managing referral programs, promoters, referrals, and tracking referral performance with advanced features like commission setting, invitation management, and Wise payouts.
Home-page: https://github.com/soldatov-ss/django-referral-system.git
Author: Soldatov Serhii
Author-email: soldatov.own@gmail.com
License: MIT
Classifier: Environment :: Web Environment
Classifier: Framework :: Django
Classifier: Framework :: Django :: 4
Classifier: Intended Audience :: Developers
Classifier: License :: OSI Approved :: MIT License
Classifier: Operating System :: OS Independent
Classifier: Programming Language :: Python
Classifier: Programming Language :: Python :: 3
Classifier: Programming Language :: Python :: 3 :: Only
Classifier: Programming Language :: Python :: 3.8
Classifier: Programming Language :: Python :: 3.9
Classifier: Programming Language :: Python :: 3.10
Classifier: Programming Language :: Python :: 3.11
Classifier: Topic :: Internet :: WWW/HTTP
Classifier: Topic :: Internet :: WWW/HTTP :: Dynamic Content
Requires-Python: >=3.8
License-File: LICENSE
Requires-Dist: Django>=4.1
Requires-Dist: djangorestframework>=3.14
Requires-Dist: pandas>=2.0
Requires-Dist: pydantic>=2.0
Requires-Dist: python-dotenv>=1.0
